watch_xfce_xfconf/__init__.py
watch_xfce_xfconf/xfconf.py
watch_xfce_xfconf/xfconf_helpers.py
watch_xfce_xfconf/xfconf_item.py
watch_xfce_xfconf-1.0.5.dist-info/LICENSE
watch_xfce_xfconf-1.0.5.dist-info/METADATA
watch_xfce_xfconf-1.0.5.dist-info/WHEEL
watch_xfce_xfconf-1.0.5.dist-info/entry_points.txt
watch_xfce_xfconf-1.0.5.dist-info/top_level.txt
watch_xfce_xfconf-1.0.5.dist-info/RECORD
