Metadata-Version: 2.1
Name: watch-xfce-xfconf
Version: 1.0.5
Summary: A command-line tool that can help you to configure XFCE 4 programmatically
Home-page: https://github.com/jamescherti/watch-xfce-xfconf
Author: James Cherti
Classifier: Development Status :: 5 - Production/Stable
Classifier: Intended Audience :: End Users/Desktop
Classifier: License :: OSI Approved :: MIT License
Classifier: Environment :: Console
Classifier: Environment :: X11 Applications
Classifier: Operating System :: POSIX :: Linux
Classifier: Operating System :: POSIX :: Other
Classifier: Topic :: Desktop Environment :: Window Managers :: XFCE
Classifier: Topic :: Desktop Environment :: Window Managers
Classifier: Programming Language :: Python :: 3 :: Only
Classifier: Programming Language :: Python :: 3
Classifier: Programming Language :: Python :: 3.6
Classifier: Programming Language :: Python :: 3.7
Classifier: Programming Language :: Python :: 3.8
Classifier: Programming Language :: Python :: 3.9
Classifier: Programming Language :: Python :: 3.10
Requires-Python: >=3.6, <4
License-File: LICENSE
Requires-Dist: lxml
Requires-Dist: psutil
